pydiscordbio/__init__.py
pydiscordbio/client.py
pydiscordbio/exceptions.py
pydiscordbio/request.py
pydiscordbio/models/__init__.py
pydiscordbio/models/discord.py
pydiscordbio/models/discord_connection.py
pydiscordbio/models/partial_user.py
pydiscordbio/models/user.py
pydiscordbio/models/user_connections.py
pydiscordbio/models/user_details.py
pydiscordbio-1.2.3.data/data/README.md
pydiscordbio-1.2.3.dist-info/LICENCE.txt
pydiscordbio-1.2.3.dist-info/METADATA
pydiscordbio-1.2.3.dist-info/WHEEL
pydiscordbio-1.2.3.dist-info/top_level.txt
pydiscordbio-1.2.3.dist-info/RECORD
