Metadata-Version: 2.1
Name: pydiscordbio
Version: 1.2.3
Summary: An unoffical asynchronous wrapper for the discord.bio API.
Home-page: https://github.com/awersli99/pydiscordbio
Author: Adam Worsley
Author-email: adam@aworsley.me
License: UNKNOWN
Platform: UNKNOWN
Requires-Dist: aiohttp (>=3.6.2)
Requires-Dist: python-dateutil (>=2.8.0)
